odoo/addons/sm_teletacs/__init__.py
odoo/addons/sm_teletacs/__manifest__.py
odoo/addons/sm_teletacs/models/__init__.py
odoo/addons/sm_teletacs/models/models_smp_teletac.py
odoo/addons/sm_teletacs/security/ir.model.access.csv
odoo/addons/sm_teletacs/views/views_teletac.xml
odoo11_addon_sm_teletacs-11.0.0.0.2.dist-info/METADATA
odoo11_addon_sm_teletacs-11.0.0.0.2.dist-info/WHEEL
odoo11_addon_sm_teletacs-11.0.0.0.2.dist-info/top_level.txt
odoo11_addon_sm_teletacs-11.0.0.0.2.dist-info/RECORD
